mongodb_connect/__init__.py
mongodb_connect/mongo_crud.py
dbconnector_python-0.0.8.dist-info/METADATA
dbconnector_python-0.0.8.dist-info/WHEEL
dbconnector_python-0.0.8.dist-info/top_level.txt
dbconnector_python-0.0.8.dist-info/RECORD
