Metadata-Version: 2.4
Name: dbconnector-python
Version: 0.0.8
Summary: A python package for connecting with database.
Home-page: https://github.com/attigeriabhishek/DB_connector
Author: attigeriabhishek
Author-email: attigeriabhishek@gmail.com
License: MIT
Project-URL: Bug Tracker, https://github.com/attigeriabhishek/DB_connector/issues
Classifier: Programming Language :: Python :: 3.12
Classifier: Programming Language :: Python :: 3.13
Classifier: Programming Language :: Python :: 3.14
Classifier: Operating System :: OS Independent
Requires-Python: >=3.12
Requires-Dist: pymongo[srv]
Requires-Dist: dnspython
Requires-Dist: pandas
Requires-Dist: numpy
Requires-Dist: ensure
Provides-Extra: testing
Requires-Dist: pytest==9.0.1; extra == "testing"
Requires-Dist: mypy==1.18.2; extra == "testing"
Requires-Dist: flake8==7.3.0; extra == "testing"
Requires-Dist: tox==4.32.0; extra == "testing"
Requires-Dist: black==25.11.0; extra == "testing"
Dynamic: author
Dynamic: author-email
Dynamic: description
Dynamic: home-page
Dynamic: project-url
Dynamic: requires-dist
Dynamic: summary
